opencensus/__init__.py
opencensus/ext/__init__.py
opencensus/ext/ocagent/__init__.py
opencensus/ext/ocagent/stats_exporter/__init__.py
opencensus/ext/ocagent/trace_exporter/__init__.py
opencensus/ext/ocagent/trace_exporter/utils.py
opencensus/ext/ocagent/utils/__init__.py
opencensus_ext_ocagent-0.7.1.dist-info/METADATA
opencensus_ext_ocagent-0.7.1.dist-info/WHEEL
opencensus_ext_ocagent-0.7.1.dist-info/namespace_packages.txt
opencensus_ext_ocagent-0.7.1.dist-info/top_level.txt
opencensus_ext_ocagent-0.7.1.dist-info/RECORD
